{
  "frontmatter": {
    "title": "46266351"
  },
  "content": {
    "source": {
      "locale": "en-US",
      "hashes": [
        "77da26a5",
        "4eab0c12",
        "cb5c44ad",
        "2a7816d0",
        "236d8040",
        "67a21e91",
        "c141c5d",
        "eea083fa",
        "cb5c44ad",
        "1e359897",
        "b19fcba1",
        "8a97ac33",
        "1529ceee",
        "59b2ab0e",
        "13769acd",
        "4ab2c29f",
        "2af178e4",
        "1f4770e5",
        "36259355"
      ]
    },
    "targets": {
      "zh-CN": [
        "77da26a5",
        "4eab0c12",
        "cb5c44ad",
        "2a7816d0",
        "236d8040",
        "67a21e91",
        "c141c5d",
        "eea083fa",
        "cb5c44ad",
        "1e359897",
        "b19fcba1",
        "8a97ac33",
        "1529ceee",
        "59b2ab0e",
        "13769acd",
        "4ab2c29f",
        "2af178e4",
        "1f4770e5",
        "36259355"
      ]
    }
  }
}
